MANIFEST.in
setup.cfg
setup.py
mdlp/__init__.py
mdlp/cmdlp.cpp
mdlp/cmdlp.cpython-35m-x86_64-linux-gnu.so
mdlp/cmdlp.pxd
mdlp/cmdlp.pyx
mdlp/mdlp.py
mdlp.egg-info/PKG-INFO
mdlp.egg-info/SOURCES.txt
mdlp.egg-info/dependency_links.txt
mdlp.egg-info/requires.txt
mdlp.egg-info/top_level.txt
tests/__init__.py
tests/test_mdlp.py